cvsets/__init__.py
cvsets/example.py
cvsets-0.0.1.dist-info/LICENSE
cvsets-0.0.1.dist-info/METADATA
cvsets-0.0.1.dist-info/WHEEL
cvsets-0.0.1.dist-info/top_level.txt
cvsets-0.0.1.dist-info/RECORD
