Metadata-Version: 2.1
Name: cvsets
Version: 0.0.1
Summary: CV algorithms with pretrained models
Home-page: https://github.com/YifeiLiu-1997/cvsets
Author: YifeiLiu-1997
Author-email: lyfwork_mail@163.com
Classifier: Programming Language :: Python :: 3
Classifier: License :: OSI Approved :: MIT License
Classifier: Operating System :: OS Independent
License-File: LICENSE
